{
  "id": "269c3fa7-28af-4568-bd94-aab5b533c880",
  "prevId": "49966f16-889a-4da4-abf9-7da39c209057",
  "version": "5",
  "dialect": "pg",
  "tables": {
    "forms": {
      "name": "forms",
      "schema": "",
      "columns": {
        "id": {
          "name": "id",
          "type": "uuid",
          "primaryKey": true,
          "notNull": true
        },
        "name": {
          "name": "name",
          "type": "varchar",
          "primaryKey": false,
          "notNull": true
        },
        "description": {
          "name": "description",
          "type": "varchar",
          "primaryKey": false,
          "notNull": true,
          "default": "'N/A'"
        }
      },
      "indexes": {},
      "foreignKeys": {},
      "compositePrimaryKeys": {},
      "uniqueConstraints": {}
    },
    "inputs": {
      "name": "inputs",
      "schema": "",
      "columns": {
        "id": {
          "name": "id",
          "type": "uuid",
          "primaryKey": true,
          "notNull": true
        },
        "label": {
          "name": "label",
          "type": "varchar",
          "primaryKey": false,
          "notNull": true
        },
        "placeholder": {
          "name": "placeholder",
          "type": "varchar",
          "primaryKey": false,
          "notNull": true
        }
      },
      "indexes": {},
      "foreignKeys": {},
      "compositePrimaryKeys": {},
      "uniqueConstraints": {}
    }
  },
  "enums": {},
  "schemas": {},
  "_meta": {
    "schemas": {},
    "tables": {},
    "columns": {}
  }
}
